MANIFEST.in
README.md
setup.py
LOGO/django_miniprogram_api.png
LOGO/zanshang.png
django_miniprogram_api.egg-info/PKG-INFO
django_miniprogram_api.egg-info/SOURCES.txt
django_miniprogram_api.egg-info/dependency_links.txt
django_miniprogram_api.egg-info/requires.txt
django_miniprogram_api.egg-info/top_level.txt
miniprogram_api/__init__.py
miniprogram_api/admin.py
miniprogram_api/apps.py
miniprogram_api/constants.py
miniprogram_api/models.py
miniprogram_api/serializers.py
miniprogram_api/tests.py
miniprogram_api/urls.py
miniprogram_api/views.py
miniprogram_api/wechat_process.py
miniprogram_api/migrations/0001_initial.py
miniprogram_api/migrations/0002_payorder.py
miniprogram_api/migrations/0003_auto_20190923_2346.py
miniprogram_api/migrations/0004_auto_20190924_0005.py
miniprogram_api/migrations/__init__.py