Metadata-Version: 2.1
Name: django-miniprogram-api
Version: 1.0.3
Summary: A simple Django app implemented the WeChat miniprogram's login, payment and other APIs
Home-page: https://github.com/TinchyChing/django_miniprogram_api
Author: Tinchy
Author-email: tinchy@yeah.net
License: BSD License
Platform: UNKNOWN
Classifier: Environment :: Web Environment
Classifier: Framework :: Django
Classifier: Framework :: Django :: 2.1
Classifier: Intended Audience :: Developers
Classifier: License :: OSI Approved :: BSD License
Classifier: Operating System :: OS Independent
Classifier: Programming Language :: Python :: 3.6
Classifier: Topic :: Internet :: WWW/HTTP
Classifier: Topic :: Internet :: WWW/HTTP :: Dynamic Content
